zinley/__init__.py
zinley/__main__.py
zinley/cli.py
zinley/version.py
zinley-0.2.2215.dist-info/LICENSE
zinley-0.2.2215.dist-info/METADATA
zinley-0.2.2215.dist-info/WHEEL
zinley-0.2.2215.dist-info/entry_points.txt
zinley-0.2.2215.dist-info/top_level.txt
zinley-0.2.2215.dist-info/RECORD
